fits_schema/__init__.py
fits_schema/binary_table.py
fits_schema/exceptions.py
fits_schema/header.py
fits_schema/primary.py
fits_schema/utils.py
tests/__init__.py
tests/test_binary_table.py
tests/test_header.py
tests/test_utils.py
fits_schema-0.5.6.dist-info/LICENSE
fits_schema-0.5.6.dist-info/METADATA
fits_schema-0.5.6.dist-info/WHEEL
fits_schema-0.5.6.dist-info/entry_points.txt
fits_schema-0.5.6.dist-info/top_level.txt
fits_schema-0.5.6.dist-info/RECORD
