Metadata-Version: 2.1
Name: fits-schema
Version: 0.5.6
Summary: A python package to define and validate schemata for FITS files.
Home-page: https://github.com/open-gamma-ray-astro/fits_schema
Author: Maximilian Nöthe
Author-email: maximilian.noethe@tu-dortmund.de
License: MIT
Platform: UNKNOWN
Classifier: License :: OSI Approved :: MIT License
Requires-Python: >=3.7
License-File: LICENSE
Requires-Dist: numpy
Requires-Dist: astropy (>=4)
Provides-Extra: all
Requires-Dist: codecov ; extra == 'all'
Requires-Dist: pyflakes ; extra == 'all'
Requires-Dist: pytest ; extra == 'all'
Requires-Dist: pytest-cov ; extra == 'all'
Provides-Extra: ci
Requires-Dist: codecov ; extra == 'ci'
Requires-Dist: pyflakes ; extra == 'ci'
Provides-Extra: tests
Requires-Dist: pytest ; extra == 'tests'
Requires-Dist: pytest-cov ; extra == 'tests'
